tmomentum/__init__.py
tmomentum/optimizers/__init__.py
tmomentum/optimizers/tadabelief.py
tmomentum/optimizers/tadabound.py
tmomentum/optimizers/tadam.py
tmomentum/optimizers/tadamw.py
tmomentum/optimizers/tdiffgrad.py
tmomentum/optimizers/tlaprop.py
tmomentum/optimizers/tpadam.py
tmomentum/optimizers/tradam.py
tmomentum/optimizers/tsadam.py
tmomentum/optimizers/tyogi.py
tmomentum/utils/__init__.py
tmomentum/utils/tmomentum.py
tmomentum-1.0.1.dist-info/METADATA
tmomentum-1.0.1.dist-info/WHEEL
tmomentum-1.0.1.dist-info/top_level.txt
tmomentum-1.0.1.dist-info/RECORD
