Metadata-Version: 2.1
Name: tmomentum
Version: 1.0.1
Summary: t-momentum
Home-page: https://github.com/Mahoumaru/t-momentum.git
Author: Wendyam Eric Lionel Ilboudo (Mahoumaru)
Author-email: lionelwendyam@yahoo.fr
License: UNKNOWN
Download-URL: https://pypi.org/manage/project/tmomentum
Platform: UNKNOWN
Requires-Dist: torch
